TAALC/__init__.py
TAALC/__main__.py
TAALC/bidding/__init__.py
TAALC/bidding/message_offer.py
TAALC/bidding/offer_state.py
TAALC/bidding/offer_type.py
TAALC/bidding/t_offer.py
TAALC/decorators.py
TAALC/finance/__init__.py
TAALC/finance/currency.py
TAALC/finance/currency_transaction.py
TAALC/finance/message_nft_token.py
TAALC/finance/message_transaction.py
TAALC/finance/nft_state.py
TAALC/finance/nft_transaction.py
TAALC/finance/taalc_nft.py
TAALC/finance/taalc_nft_token.py
TAALC/finance/taalc_token.py
TAALC/finance/taalc_transaction.py
TAALC/finance/tokens_bag.py
TAALC/finance/transaction_batch.py
TAALC/finance/wallet.py
TAALC/handlers/__init__.py
TAALC/handlers/administration.py
TAALC/handlers/check_balance.py
TAALC/handlers/gift.py
TAALC/handlers/offer.py
TAALC/taalc_bot.py
TAALC/taalc_error.py
TAALC/teest/__init__.py
TAALC/teest/bot_response.py
TAALC/teest/tester.py
TAALC/teest/testing_message.py
TAALC/tests/__init__.py
TAALC/tests/test_gift.py
TAALC/tg_environment/t_chat.py
TAALC/tg_environment/t_member.py
TAALC/tg_environment/t_message.py
TAALC/tg_environment/t_user.py
TAALC/tg_environment/telegram_entity.py
TAALC/worker.py
taalc-0.1.32.dist-info/METADATA
taalc-0.1.32.dist-info/WHEEL
taalc-0.1.32.dist-info/RECORD
