Metadata-Version: 2.3
Name: TAALC
Version: 0.1.32
Summary: 
Author: Nikita Umerov
Author-email: nagvalhm@yandex.ru
Requires-Python: >=3.10,<4.0
Classifier: Programming Language :: Python :: 3
Classifier: Programming Language :: Python :: 3.10
Classifier: Programming Language :: Python :: 3.11
Classifier: Programming Language :: Python :: 3.12
Classifier: Programming Language :: Python :: 3.13
Requires-Dist: aiogram (>=3.20.0.post0,<4.0.0)
Requires-Dist: epure (>=0.3.12,<0.4.0)
Requires-Dist: pytest (>=8.3.5,<9.0.0)
Requires-Dist: pytest-asyncio (>=1.0.0,<2.0.0)
Project-URL: Homepage, https://github.com/nagvalhm/TAALC
Project-URL: Source, https://github.com/nagvalhm/TAALC
